ragdefender/__init__.py
ragdefender/cli.py
ragdefender/attacks/__init__.py
ragdefender/core/__init__.py
ragdefender/core/defender.py
ragdefender/core/evaluator.py
ragdefender/datasets/__init__.py
ragdefender/defenses/__init__.py
ragdefender/models/__init__.py
ragdefender-0.1.1.dist-info/LICENSE
ragdefender-0.1.1.dist-info/METADATA
ragdefender-0.1.1.dist-info/WHEEL
ragdefender-0.1.1.dist-info/entry_points.txt
ragdefender-0.1.1.dist-info/top_level.txt
ragdefender-0.1.1.dist-info/RECORD
