Metadata-Version: 2.1
Name: ragdefender
Version: 0.1.1
Summary: Efficient defense against knowledge corruption attacks on RAG systems
Home-page: https://github.com/SecAI-Lab/RAGDefender
Author: SecAI Lab
Author-email: SecAI Lab <for8821@g.skku.edu>
Maintainer-email: Minseok Kim <for8821@g.skku.edu>
License: MIT
Project-URL: Homepage, https://github.com/SecAI-Lab/RAGDefender
Project-URL: Documentation, https://github.com/SecAI-Lab/RAGDefender/tree/main/docs
Project-URL: Repository, https://github.com/SecAI-Lab/RAGDefender.git
Project-URL: Bug Tracker, https://github.com/SecAI-Lab/RAGDefender/issues
Project-URL: Paper, https://arxiv.org/abs/YOUR_PAPER_URL
Keywords: rag,retrieval-augmented-generation,security,adversarial-defense,nlp,machine-learning,knowledge-corruption,llm
Classifier: Development Status :: 3 - Alpha
Classifier: Intended Audience :: Developers
Classifier: Intended Audience :: Science/Research
Classifier: Topic :: Scientific/Engineering :: Artificial Intelligence
Classifier: Topic :: Security
Classifier: Topic :: Software Development :: Libraries :: Python Modules
Classifier: License :: OSI Approved :: MIT License
Classifier: Programming Language :: Python :: 3
Classifier: Programming Language :: Python :: 3.8
Classifier: Programming Language :: Python :: 3.9
Classifier: Programming Language :: Python :: 3.10
Classifier: Programming Language :: Python :: 3.11
Classifier: Operating System :: OS Independent
Requires-Python: >=3.8
License-File: LICENSE
Requires-Dist: torch>=1.9.0
Requires-Dist: transformers>=4.20.0
Requires-Dist: numpy>=1.19.0
Requires-Dist: pandas>=1.2.0
Requires-Dist: tqdm>=4.60.0
Requires-Dist: scikit-learn>=0.24.0
Requires-Dist: sentence-transformers>=2.2.0
Provides-Extra: all
Requires-Dist: ragdefender[dev]; extra == "all"
Requires-Dist: ragdefender[cuda]; extra == "all"
Requires-Dist: ragdefender[docs]; extra == "all"
Provides-Extra: cuda
Requires-Dist: faiss-gpu>=1.7.0; extra == "cuda"
Provides-Extra: dev
Requires-Dist: pytest>=6.0; extra == "dev"
Requires-Dist: pytest-cov>=2.10; extra == "dev"
Requires-Dist: black>=21.0; extra == "dev"
Requires-Dist: flake8>=3.9; extra == "dev"
Requires-Dist: isort>=5.9; extra == "dev"
Requires-Dist: mypy>=0.900; extra == "dev"
Requires-Dist: pre-commit>=2.15; extra == "dev"
Provides-Extra: docs
Requires-Dist: sphinx>=4.0; extra == "docs"
Requires-Dist: sphinx-rtd-theme>=0.5; extra == "docs"
Requires-Dist: sphinx-autodoc-typehints>=1.12; extra == "docs"
